jesusgraph/__init__.py
jesusgraph/jesusGraph.py
jesusgraph/core/__init__.py
jesusgraph/core/blessingstate.py
jesusgraph/core/execution.py
jesusgraph/core/graph.py
jesusgraph-0.1.4.dist-info/METADATA
jesusgraph-0.1.4.dist-info/WHEEL
jesusgraph-0.1.4.dist-info/top_level.txt
jesusgraph-0.1.4.dist-info/RECORD
