Metadata-Version: 2.4
Name: jesusgraph
Version: 0.1.4
Summary: Um orquestrador de fluxos inspirado pela fé, propósito e clareza.
Author-email: Carlos Viana <suporte@carlosviana.com>
License: MIT
Project-URL: Homepage, https://github.com/ITValley-School/Jesusgraph
Requires-Python: >=3.8
Requires-Dist: requests>=2.25.1
